psga.py
psga-0.0.7.dist-info/LICENSE
psga-0.0.7.dist-info/METADATA
psga-0.0.7.dist-info/WHEEL
psga-0.0.7.dist-info/top_level.txt
psga-0.0.7.dist-info/RECORD
