Metadata-Version: 2.1
Name: psga
Version: 0.0.7
Summary: Smarter event handling for PySimpleGUI
Author-email: F M <psga@mikmak.fun>
Project-URL: Homepage, https://github.com/aptly-io/psga
Project-URL: Bug Tracker, https://github.com/aptly-io/psga/issues
Classifier: Programming Language :: Python :: 3
Classifier: Intended Audience :: Developers
Classifier: License :: OSI Approved :: MIT License
Classifier: Operating System :: OS Independent
Classifier: Programming Language :: Python :: 3.8
Classifier: Programming Language :: Python :: 3.9
Classifier: Programming Language :: Python :: 3.10
Classifier: Programming Language :: Python :: 3.11
Classifier: Programming Language :: Python :: 3.12
Classifier: Framework :: PySimpleGUI
Classifier: Framework :: PySimpleGUI :: 4
Requires-Python: >=3.8
License-File: LICENSE
Requires-Dist: PySimpleGUI
Requires-Dist: typing-extensions
Provides-Extra: demo
Requires-Dist: fastapi ==0.109.1 ; extra == 'demo'
Requires-Dist: pydantic ==2.6.0 ; extra == 'demo'
Requires-Dist: uvicorn ==0.27.0.post1 ; extra == 'demo'
Provides-Extra: test
Requires-Dist: isort ; extra == 'test'
Requires-Dist: black ; extra == 'test'
Requires-Dist: pylint ; extra == 'test'
Requires-Dist: pytest ; extra == 'test'
Requires-Dist: pytest-mock ; extra == 'test'
Requires-Dist: pytest-cov ; extra == 'test'
Requires-Dist: build ; extra == 'test'
Requires-Dist: twine ; extra == 'test'
